{
	"tech_data": [
		{
			"key": "contract-vehicle-brand-value",
			"value": "Mercedes-Benz C 220"
		},
		{
			"key": "contract-vehicle-first-registration-value",
			"value": "04/2008"
		},
		{
			"key": "contract-vehicle-vehicle-type-value",
			"value": "Limousine"
		},
		{
			"key": "contract-vehicle-fuel-type-value",
			"value": "Diesel"
		},
		{
			"key": "contract-vehicle-climate-control-value",
			"value": "2-Zonen-Klimaautomatik"
		},
		{
			"key": "contract-vehicle-gear-type-value",
			"value": "Schaltgetriebe"
		},
		{
			"key": "contract-vehicle-color-value",
			"value": "Schwarz Metallic"
		},
		{
			"key": "contract-vehicle-number-of-doors-value",
			"value": "4/5"
		},
		{
			"key": "contract-vehicle-cubic-capacity-value",
			"value": "2.148 cm³"
		},
		{
			"key": "contract-vehicle-total-mileage-value",
			"value": "348.000 km"
		},
		{
			"key": "contract-vehicle-performance-value",
			"value": "125 kW (170 PS)"
		},
		{
			"key": "contract-vehicle-performance-value-delta",
			"value": 10
		},
		{
			"key": "contract-vehicle-emission-class-value",
			"value": "Euro4"
		}
	],
	"car_features": [
		"Navigationssystem",
		"Panorama-Dach",
		"LED-Scheinwerfer",
		"Xenonscheinwerfer",
		"Bi-Xenon Scheinwerfer",
		"Allradantrieb",
		"Schiebedach",
		"Alcantara",
		"Teilleder",
		"Vollleder",
		"ABS",
		"Abstandswarner",
		"Adaptives Kurvenlicht"
	]
}